{
  "schemaVersion": 1,
  "curveSetId": "curve-channel-evolution-channel-evolution-model-stage-i-vi",
  "metricId": "channel-evolution-channel-evolution-model-stage-i-vi",
  "tier": "screening",
  "name": "Screening default curve",
  "axes": {
    "xLabel": "Metric category",
    "yLabel": "Index score"
  },
  "curves": [
    {
      "curveId": "curve-channel-evolution-channel-evolution-model-stage-i-vi-default",
      "name": "Screening",
      "xType": "qualitative",
      "units": "",
      "layers": [
        {
          "id": "curve-channel-evolution-channel-evolution-model-stage-i-vi-layer",
          "name": "Screening",
          "points": [
            {
              "x": "Optimal",
              "y": 1,
              "description": "Stable or re-stabilized channel (Stage I or VI)."
            },
            {
              "x": "Suboptimal",
              "y": 0.69,
              "description": "Partially recovered channel (often Stage V)."
            },
            {
              "x": "Marginal",
              "y": 0.3,
              "description": "Actively widening or incising (often Stage III-IV)."
            },
            {
              "x": "Poor",
              "y": 0,
              "description": "Severe incision or destructive phases (often Stage II or severe III-IV)."
            }
          ]
        }
      ],
      "activeLayerId": "curve-channel-evolution-channel-evolution-model-stage-i-vi-layer"
    }
  ]
}