{
  "schemaVersion": 1,
  "curveSetId": "curve-habitat-provision-pool-spacing-ratio-for-c-and-e-stream-types-detailed",
  "metricId": "habitat-provision-pool-spacing-ratio-for-c-and-e-stream-types-detailed",
  "tier": "detailed",
  "name": "Pool Spacing Ratio for C and E Stream Types reference curve",
  "axes": {
    "xLabel": "Pool Spacing Ratio for C and E Stream Types",
    "yLabel": "Index score",
    "yUnit": "index"
  },
  "curves": [
    {
      "curveId": "curve-habitat-provision-pool-spacing-ratio-for-c-and-e-stream-types-detailed-default",
      "name": "Detailed reference",
      "xType": "quantitative",
      "units": "",
      "indexRange": false,
      "layers": [
        {
          "id": "curve-habitat-provision-pool-spacing-ratio-for-c-and-e-stream-types-detailed-multiple-sqts",
          "name": "Multiple SQTs",
          "points": [
            {
              "x": 1,
              "y": 0,
              "description": "Field 1, Index 0"
            },
            {
              "x": 3.5,
              "y": 1,
              "description": "Field 3.5, Index 1"
            }
          ],
          "sourceMetadata": {
            "stratification": "Multiple SQTs",
            "sourceRow": 351,
            "sourceRows": [
              351,
              364
            ],
            "sourceCitation": "South Carolina SQT",
            "sourceCitations": [
              "South Carolina SQT",
              "Wisconsin SQT"
            ],
            "fieldValues": [
              "1",
              "",
              "",
              "",
              "",
              "3.5",
              ""
            ],
            "indexValues": [
              "0",
              "0.39",
              "0.4",
              "0.69",
              "0.7",
              "1",
              ""
            ]
          }
        }
      ],
      "activeLayerId": "curve-habitat-provision-pool-spacing-ratio-for-c-and-e-stream-types-detailed-multiple-sqts"
    }
  ],
  "sourceMetadata": {
    "importSource": "detailed-metrics-source-rich.tsv",
    "sourceCitation": "South Carolina SQT; Wisconsin SQT",
    "sourceCitations": [
      "South Carolina SQT",
      "Wisconsin SQT"
    ],
    "mappedFunction": "Habitat provision",
    "sourceRows": [
      351,
      364
    ]
  }
}
