{
  "schemaVersion": 1,
  "curveSetId": "curve-high-flow-dynamics-peak-flow-capacity-morphological-check-rapid",
  "metricId": "high-flow-dynamics-peak-flow-capacity-morphological-check",
  "tier": "rapid",
  "name": "Peak Flow Capacity (Morphological Check) rapid curve",
  "axes": {
    "xLabel": "Metric category",
    "yLabel": "Index score"
  },
  "curves": [
    {
      "curveId": "curve-high-flow-dynamics-peak-flow-capacity-morphological-check-rapid-default",
      "name": "SFARI rapid scoring",
      "xType": "qualitative",
      "units": "",
      "layers": [
        {
          "id": "curve-high-flow-dynamics-peak-flow-capacity-morphological-check-rapid-sfari-rapid",
          "name": "SFARI Rapid",
          "points": [
            {
              "x": "Strongly Agree",
              "y": 0.92,
              "yMin": 0.84,
              "yMax": 1,
              "description": "Observation: Bankfull width and depth closely match regional curves for the drainage area and slope. Bars and banks remain stable through ~1-2 yr flows. Criteria: Near regional curve; stable"
            },
            {
              "x": "Agree",
              "y": 0.735,
              "yMin": 0.64,
              "yMax": 0.83,
              "description": "Observation: Slightly oversized or undersized relative to curves. Isolated bank slumps after moderate events. Criteria: Mild departure; occasional instability"
            },
            {
              "x": "Neutral",
              "y": 0.535,
              "yMin": 0.44,
              "yMax": 0.63,
              "description": "Criteria: Neutral / mixed evidence."
            },
            {
              "x": "Disagree",
              "y": 0.335,
              "yMin": 0.24,
              "yMax": 0.43,
              "description": "Observation: Noticeable mismatch to curves. Frequent bar growth or cutbank retreat after moderate events. Criteria: Significant departure; frequent instability"
            },
            {
              "x": "Strongly Disagree",
              "y": 0.115,
              "yMin": 0,
              "yMax": 0.23,
              "description": "Observation: Highly out of family. Repeated blowouts, chute formation, or bank failures with moderate floods. Criteria: Severe departure; chronic instability"
            }
          ]
        }
      ],
      "activeLayerId": "curve-high-flow-dynamics-peak-flow-capacity-morphological-check-rapid-sfari-rapid",
      "indexRange": true
    }
  ]
}
