{
  "schemaVersion": 1,
  "curveSetId": "curve-carbon-processing-riparian-vegetation-stem-density-detailed",
  "metricId": "carbon-processing-riparian-vegetation-stem-density-detailed",
  "tier": "detailed",
  "name": "Riparian Vegetation Stem Density reference curve",
  "axes": {
    "xLabel": "Riparian Vegetation Stem Density",
    "yLabel": "Index score",
    "yUnit": "index"
  },
  "curves": [
    {
      "curveId": "curve-carbon-processing-riparian-vegetation-stem-density-detailed-default",
      "name": "Detailed reference",
      "xType": "quantitative",
      "units": "",
      "indexRange": false,
      "layers": [
        {
          "id": "curve-carbon-processing-riparian-vegetation-stem-density-detailed-north-carolina-sqt",
          "name": "North Carolina SQT",
          "points": [
            {
              "x": 0,
              "y": 0,
              "description": "Field 0, Index 0"
            },
            {
              "x": 260,
              "y": 0.5,
              "description": "Field 260, Index 0.5"
            }
          ],
          "sourceMetadata": {
            "stratification": "",
            "sourceRow": 210,
            "sourceRows": [
              210
            ],
            "sourceCitation": "North Carolina SQT",
            "sourceCitations": [
              "North Carolina SQT"
            ],
            "fieldValues": [
              "0",
              "",
              "",
              "260",
              "",
              "",
              ""
            ],
            "indexValues": [
              "0",
              "0.29",
              "0.3",
              "0.5",
              "0.7",
              "1",
              ""
            ]
          }
        }
      ],
      "activeLayerId": "curve-carbon-processing-riparian-vegetation-stem-density-detailed-north-carolina-sqt"
    }
  ],
  "sourceMetadata": {
    "importSource": "detailed-metrics-source-rich.tsv",
    "sourceCitation": "North Carolina SQT",
    "sourceCitations": [
      "North Carolina SQT"
    ],
    "mappedFunction": "Carbon processing",
    "sourceRows": [
      210
    ]
  }
}