{
  "curves": [
    {
      "indexRange": true,
      "layers": [
        {
          "name": "Screening",
          "points": [
            {
              "x": "Optimal",
              "description": "No active headcuts. Any legacy headcuts are stable.",
              "yMax": 1.0,
              "yMin": 0.76,
              "y": 1
            },
            {
              "x": "Suboptimal",
              "description": "Small local headcuts with limited progression potential.",
              "yMax": 0.75,
              "yMin": 0.5,
              "y": 0.69
            },
            {
              "x": "Marginal",
              "description": "One or two active headcuts with noticeable vertical instability.",
              "yMax": 0.49,
              "yMin": 0.25,
              "y": 0.3
            },
            {
              "x": "Poor",
              "description": "Multiple or large active headcuts rapidly advancing and driving incision and failures.",
              "yMax": 0.24,
              "yMin": 0.0,
              "y": 0
            }
          ],
          "id": "curve-channel-evolution-incision-trend-layer"
        }
      ],
      "xType": "categorical",
      "curveId": "curve-channel-evolution-incision-trend-default",
      "name": "Screening",
      "units": "",
      "activeLayerId": "curve-channel-evolution-incision-trend-layer"
    }
  ],
  "schemaVersion": 1,
  "name": "Screening default curve",
  "curveSetId": "curve-channel-evolution-incision-trend",
  "tier": "screening",
  "axes": {
    "xLabel": "Metric category",
    "yLabel": "Index score"
  },
  "metricId": "channel-evolution-incision-trend"
}
